elementally/__init__.py
elementally_DEMcKnight-0.2.dist-info/LICENSE
elementally_DEMcKnight-0.2.dist-info/METADATA
elementally_DEMcKnight-0.2.dist-info/WHEEL
elementally_DEMcKnight-0.2.dist-info/top_level.txt
elementally_DEMcKnight-0.2.dist-info/RECORD
